spath/__init__.py
spath/spath.py
spath-0.1.5.dist-info/AUTHORS.rst
spath-0.1.5.dist-info/LICENSE
spath-0.1.5.dist-info/METADATA
spath-0.1.5.dist-info/WHEEL
spath-0.1.5.dist-info/top_level.txt
spath-0.1.5.dist-info/RECORD
