Metadata-Version: 2.1
Name: spath
Version: 0.1.5
Summary: Extras for path.py
Home-page: https://github.com/dimatura/spath.py
Author: Daniel Maturana
Author-email: dimatura@cmu.edu
License: BSD license
Download-URL: https://github.com/dimatura/spath.py/tarball/0.1.5.zip
Keywords: spath
Platform: UNKNOWN
Classifier: Development Status :: 2 - Pre-Alpha
Classifier: Intended Audience :: Developers
Classifier: License :: OSI Approved :: BSD License
Classifier: Natural Language :: English
Classifier: Programming Language :: Python :: 2
Classifier: Programming Language :: Python :: 2.6
Classifier: Programming Language :: Python :: 2.7
Classifier: Programming Language :: Python :: 3
Classifier: Programming Language :: Python :: 3.3
Classifier: Programming Language :: Python :: 3.4
Classifier: Programming Language :: Python :: 3.5
Requires-Dist: six
Requires-Dist: path.py
Requires-Dist: humanize
Requires-Dist: pillow
